odoo10_addon_rest_log-10.0.1.3.1-py3.8-nspkg.pth
odoo/addons/rest_log/README.rst
odoo/addons/rest_log/__init__.py
odoo/addons/rest_log/__manifest__.py
odoo/addons/rest_log/exceptions.py
odoo/addons/rest_log/components/__init__.py
odoo/addons/rest_log/components/service.py
odoo/addons/rest_log/data/ir_config_parameter_data.xml
odoo/addons/rest_log/data/ir_cron_data.xml
odoo/addons/rest_log/models/__init__.py
odoo/addons/rest_log/models/ir_config_parameter.py
odoo/addons/rest_log/models/rest_log.py
odoo/addons/rest_log/readme/CONFIGURE.rst
odoo/addons/rest_log/readme/CONTRIBUTORS.rst
odoo/addons/rest_log/readme/CREDITS.rst
odoo/addons/rest_log/readme/DESCRIPTION.rst
odoo/addons/rest_log/readme/HISTORY.rst
odoo/addons/rest_log/security/groups.xml
odoo/addons/rest_log/security/ir.model.access.csv
odoo/addons/rest_log/static/description/icon.png
odoo/addons/rest_log/static/description/index.html
odoo/addons/rest_log/tests/__init__.py
odoo/addons/rest_log/tests/common.py
odoo/addons/rest_log/tests/test_db_logging.py
odoo/addons/rest_log/tests/tools.py
odoo/addons/rest_log/views/menu.xml
odoo/addons/rest_log/views/rest_log_views.xml
odoo10_addon_rest_log-10.0.1.3.1.dist-info/METADATA
odoo10_addon_rest_log-10.0.1.3.1.dist-info/WHEEL
odoo10_addon_rest_log-10.0.1.3.1.dist-info/namespace_packages.txt
odoo10_addon_rest_log-10.0.1.3.1.dist-info/top_level.txt
odoo10_addon_rest_log-10.0.1.3.1.dist-info/RECORD
