Metadata-Version: 2.1
Name: odoo10-addon-rest-log
Version: 10.0.1.3.1
Summary: Track REST API calls into DB
Home-page: https://github.com/OCA/rest-framework
Author: Camptocamp, ACSONE, Odoo Community Association (OCA)
Author-email: support@odoo-community.org
License: LGPL-3
Platform: UNKNOWN
Classifier: Programming Language :: Python
Classifier: Framework :: Odoo
Classifier: License :: OSI Approved :: GNU Lesser General Public License v3 (LGPLv3)
Classifier: Development Status :: 3 - Alpha
Requires-Python: ~=2.7
Requires-Dist: odoo10-addon-base-rest
Requires-Dist: odoo (<10.1dev,>=10.0)
